workspace/__init__.py
workspace/config.py
workspace/controller.py
workspace/scm.py
workspace/utils.py
workspace/commands/__init__.py
workspace/commands/bump.py
workspace/commands/checkout.py
workspace/commands/clean.py
workspace/commands/commit.py
workspace/commands/diff.py
workspace/commands/helpers.py
workspace/commands/log.py
workspace/commands/merge.py
workspace/commands/publish.py
workspace/commands/push.py
workspace/commands/setup.py
workspace/commands/status.py
workspace/commands/test.py
workspace/commands/update.py
workspace_tools-3.4.2.dist-info/LICENSE
workspace_tools-3.4.2.dist-info/METADATA
workspace_tools-3.4.2.dist-info/WHEEL
workspace_tools-3.4.2.dist-info/entry_points.txt
workspace_tools-3.4.2.dist-info/top_level.txt
workspace_tools-3.4.2.dist-info/RECORD
