Metadata-Version: 2.1
Name: workspace-tools
Version: 3.4.2
Summary: Convenience wrapper for git/tox to simplify local development
Home-page: https://github.com/maxzheng/workspace-tools
Author: Max Zheng
Author-email: maxzheng.os@gmail.com
License: MIT
Keywords: workspace multiple repositories git tox wrapper development tools
Classifier: Development Status :: 5 - Production/Stable
Classifier: Intended Audience :: Developers
Classifier: Topic :: Software Development
Classifier: License :: OSI Approved :: MIT License
Classifier: Programming Language :: Python :: 3.6
Requires-Python: >=3.6
License-File: LICENSE
Requires-Dist: bumper-lib (>=2)
Requires-Dist: click
Requires-Dist: GitPython
Requires-Dist: localconfig (>=1)
Requires-Dist: remoteconfig (>=1)
Requires-Dist: requests
Requires-Dist: six
Requires-Dist: utils-core
